sage_data_client/__init__.py
sage_data_client/query.py
sage_data_client-0.9.0.dist-info/LICENSE
sage_data_client-0.9.0.dist-info/METADATA
sage_data_client-0.9.0.dist-info/WHEEL
sage_data_client-0.9.0.dist-info/top_level.txt
sage_data_client-0.9.0.dist-info/RECORD
