Metadata-Version: 2.1
Name: sage-data-client
Version: 0.9.0
Summary: Official Sage data client.
Home-page: https://github.com/sagecontinuum/sage-data-client
Author: Sean Shahkarami
Author-email: sean.shahkarami@gmail.com
Project-URL: Bug Tracker, https://github.com/sagecontinuum/sage-data-client/issues
Classifier: Programming Language :: Python :: 3
Classifier: License :: OSI Approved :: BSD License
Classifier: Operating System :: OS Independent
Requires-Python: >=3.6
License-File: LICENSE
Requires-Dist: pandas>=2.0.0
